qdiction/__init__.py
qdiction/__main__.py
qdiction/dict_project.py
qdiction/dictionary_auto_gen.py
qdiction/icons/__init__.py
QDiction-2.0.1.dist-info/LICENSE
QDiction-2.0.1.dist-info/METADATA
QDiction-2.0.1.dist-info/WHEEL
QDiction-2.0.1.dist-info/top_level.txt
QDiction-2.0.1.dist-info/RECORD
