Metadata-Version: 2.1
Name: QDiction
Version: 2.0.1
Summary: A dictionary application based on wordnet and NLTK
Author-email: ro_alli <ro_alli@protonmail.com>
Requires-Python: >=3.6
License-File: LICENSE
